fin_traffic_data/__init__.py
fin_traffic_data/aggregation.py
fin_traffic_data/metadata.py
fin_traffic_data/raw_data.py
fin_traffic_data/utils.py
fin_traffic_data/data/__init__.py
fin_traffic_data/data/erva_coordinates.csv
fin_traffic_data/data/municipality_info.csv
fin_traffic_data/data/municipality_neighbours.json
fin_traffic_data/data/province_info.csv
fin_traffic_data/data/tms_over_erva_borders.csv
fin_traffic_data/data/tms_over_province_borders.csv
fin_traffic_data/scripts/__init__.py
fin_traffic_data/scripts/aggregate_raw_data.py
fin_traffic_data/scripts/export_area_data_as_csv.py
fin_traffic_data/scripts/fetch_raw_data.py
fin_traffic_data/scripts/get_aggregated_traffic_between_areas.py
fin_traffic_data-0.0.5.dist-info/METADATA
fin_traffic_data-0.0.5.dist-info/WHEEL
fin_traffic_data-0.0.5.dist-info/entry_points.txt
fin_traffic_data-0.0.5.dist-info/top_level.txt
fin_traffic_data-0.0.5.dist-info/zip-safe
fin_traffic_data-0.0.5.dist-info/RECORD
