Metadata-Version: 2.1
Name: fin-traffic-data
Version: 0.0.5
Summary: Fetching and aggregation of traffic data from Finnish roads
Home-page: https://www.solanpaa.fi
Author: Janne Solanpää
Author-email: janne@solanpaa.fi
License: MIT
Platform: UNKNOWN
Classifier: Environment :: Console
Classifier: Intended Audience :: Developers
Classifier: License :: Other/Proprietary License
Classifier: Operating System :: OS Independent
Classifier: Programming Language :: Python :: 3 :: Only
Classifier: Programming Language :: Python :: 3.8
Requires-Python: >=3.7
Requires-Dist: networkx
Requires-Dist: progressbar2
Requires-Dist: pandas
Requires-Dist: numpy
Requires-Dist: scipy
Requires-Dist: matplotlib
Requires-Dist: requests
Requires-Dist: h5py
Requires-Dist: tables
Requires-Dist: mypy
Requires-Dist: tqdm
